awsclientbot/__init__.py
awsclientbot-0.1.0.dist-info/DESCRIPTION.rst
awsclientbot-0.1.0.dist-info/METADATA
awsclientbot-0.1.0.dist-info/RECORD
awsclientbot-0.1.0.dist-info/WHEEL
awsclientbot-0.1.0.dist-info/metadata.json
awsclientbot-0.1.0.dist-info/top_level.txt
