Metadata-Version: 2.0
Name: awsclientbot
Version: 0.1.0
Summary: Client for AWS Client Bot
Home-page: https://github.com/tertychnyy/awsclientbot
Author: Ivan Tertychnyy
Author-email: itertychnyy@gmail.com
License: LICENSE.txt
Project-URL: Documentation, http://awsclientbot.readthedocs.io/en/latest/
Project-URL: Tracker, https://github.com/tertychnyy/awsclientbot/issues
Platform: UNKNOWN
Requires-Dist: requests (>=2.10.0)
